addressable_sql_queries/__init__.py
addressable_sql_queries/__main__.py
addressable_sql_queries/default_python_basis.py
addressable_sql_queries-0.0.1.dev1.dist-info/METADATA
addressable_sql_queries-0.0.1.dev1.dist-info/WHEEL
addressable_sql_queries-0.0.1.dev1.dist-info/licenses/LICENSE
addressable_sql_queries-0.0.1.dev1.dist-info/RECORD
