Metadata-Version: 2.1
Name: addressable-sql-queries
Version: 0.0.1.dev1
Summary: Individualize the queries of a SQL script and make them easily addressable
Author: Jean Oustry
License: MIT License
License-File: LICENSE
Keywords: SQL,addressable queries,addressable query,parser,preprocessor,script chunk,script manipulation
Classifier: License :: OSI Approved :: MIT License
Classifier: Operating System :: OS Independent
Classifier: Programming Language :: Python :: 3
Requires-Python: >=3.10
Provides-Extra: test
Requires-Dist: autopep8; extra == 'test'
Requires-Dist: build; extra == 'test'
Requires-Dist: coverage; extra == 'test'
Requires-Dist: mypy; extra == 'test'
Requires-Dist: setuptools; extra == 'test'
Requires-Dist: twine; extra == 'test'
Requires-Dist: wheel; extra == 'test'
